cmpy
