Metadata-Version: 1.1
Name: cmpy
Version: 0.2
Summary: A simple utility for detecting differences in directories and files.
Home-page: https://github.com/edaniszewski/cmpy
Author: Erick Daniszewski
Author-email: edaniszewski@gmail.com
License: MIT
Download-URL: https://github.com/edaniszewski/cmpy/releases/tag/0.2
Keywords: file compare,directory compare,compare,comparison
Platform: UNKNOWN
Classifier: Intended Audience :: Developers
Classifier: License :: OSI Approved :: MIT License
Classifier: Natural Language :: English
Classifier: Programming Language :: Python
Classifier: Programming Language :: Python :: 2
Classifier: Programming Language :: Python :: 2.7
Classifier: Topic :: Utilities
